{
  "data": {
    "article": {},
    "attachments": {},
    "author_id": "1972363680198361088",
    "conversation_id": "1985272214443430262",
    "created_at": "2025-11-03T10:52:34.000Z",
    "edit_controls": {
      "editable_until": "2025-11-03T11:52:34.000Z",
      "edits_remaining": 5,
      "is_edit_eligible": false
    },
    "edit_history_tweet_ids": [
      "1985299055786983805"
    ],
    "entities": {
      "mentions": [
        {
          "end": 10,
          "id": "1893026488662007810",
          "start": 0,
          "username": "youmu0187"
        }
      ]
    },
    "geo": {},
    "id": "1985299055786983805",
    "in_reply_to_user_id": "1893026488662007810",
    "lang": "zh",
    "note_tweet": {
      "entities": {}
    },
    "possibly_sensitive": false,
    "public_metrics": {
      "bookmark_count": 0,
      "impression_count": 0,
      "like_count": 0,
      "quote_count": 0,
      "reply_count": 0,
      "retweet_count": 0
    },
    "referenced_tweets": [
      {
        "id": "1985297907659182400",
        "type": "replied_to"
      }
    ],
    "reply_settings": "everyone",
    "text": "@youmu0187 安心是指氛围呢，推特在戾气较小（某些区域除外）的同时又很有氛围而且会怀着立场相互攻讦的情况相对其他平台而言似乎不算多（某些区域除外）\n至于碎碎念…热度高了的碎碎念直接隐藏不就好了嘛（况且绝对不想被看见的内容是绝对会避免发出来的）"
  },
  "includes": {
    "tweets": [
      {
        "article": {},
        "attachments": {},
        "author_id": "1972363680198361088",
        "conversation_id": "1985272214443430262",
        "created_at": "2025-11-03T10:52:34.000Z",
        "edit_controls": {
          "editable_until": "2025-11-03T11:52:34.000Z",
          "edits_remaining": 5,
          "is_edit_eligible": false
        },
        "edit_history_tweet_ids": [
          "1985299055786983805"
        ],
        "entities": {
          "mentions": [
            {
              "end": 10,
              "id": "1893026488662007810",
              "start": 0,
              "username": "youmu0187"
            }
          ]
        },
        "geo": {},
        "id": "1985299055786983805",
        "in_reply_to_user_id": "1893026488662007810",
        "lang": "zh",
        "note_tweet": {
          "entities": {}
        },
        "possibly_sensitive": false,
        "public_metrics": {
          "bookmark_count": 0,
          "impression_count": 0,
          "like_count": 0,
          "quote_count": 0,
          "reply_count": 0,
          "retweet_count": 0
        },
        "referenced_tweets": [
          {
            "id": "1985297907659182400",
            "type": "replied_to"
          }
        ],
        "reply_settings": "everyone",
        "text": "@youmu0187 安心是指氛围呢，推特在戾气较小（某些区域除外）的同时又很有氛围而且会怀着立场相互攻讦的情况相对其他平台而言似乎不算多（某些区域除外）\n至于碎碎念…热度高了的碎碎念直接隐藏不就好了嘛（况且绝对不想被看见的内容是绝对会避免发出来的）"
      },
      {
        "article": {},
        "attachments": {},
        "author_id": "1893026488662007810",
        "conversation_id": "1985272214443430262",
        "created_at": "2025-11-03T10:48:00.000Z",
        "edit_controls": {
          "editable_until": "2025-11-03T11:48:00.000Z",
          "edits_remaining": 5,
          "is_edit_eligible": false
        },
        "edit_history_tweet_ids": [
          "1985297907659182400"
        ],
        "entities": {
          "mentions": [
            {
              "end": 12,
              "id": "1972363680198361088",
              "start": 0,
              "username": "dnshu135734"
            }
          ]
        },
        "geo": {},
        "id": "1985297907659182400",
        "in_reply_to_user_id": "1972363680198361088",
        "lang": "zh",
        "note_tweet": {
          "entities": {}
        },
        "possibly_sensitive": false,
        "public_metrics": {
          "bookmark_count": 0,
          "impression_count": 9,
          "like_count": 2,
          "quote_count": 0,
          "reply_count": 1,
          "retweet_count": 0
        },
        "referenced_tweets": [
          {
            "id": "1985272214443430262",
            "type": "replied_to"
          }
        ],
        "reply_settings": "everyone",
        "text": "@dnshu135734 没被关注的时候确实如此——但如果不愿被看见又为何要选择社交平台呢，所以关注数的多与少便成了件很矛盾的事情"
      }
    ],
    "users": [
      {
        "created_at": "2025-09-28T18:12:15.000Z",
        "description": "嗯………不喜欢给自己加标签但是看起来肯定很极端的废物吧",
        "id": "1972363680198361088",
        "name": "淡水",
        "pinned_tweet_id": "1975496238289354976",
        "profile_image_url": "https://pbs.twimg.com/profile_images/1973384690410356736/1F0gknLf_normal.jpg",
        "protected": false,
        "public_metrics": {
          "followers_count": 3,
          "following_count": 3,
          "like_count": 531,
          "listed_count": 0,
          "media_count": 9,
          "tweet_count": 202
        },
        "username": "dnshu135734",
        "verified": false
      },
      {
        "created_at": "2025-02-21T19:54:32.000Z",
        "description": "不定期存放点随笔，偶尔去发现些有趣事情，需回fo可私信或留言。小号：@AnonChishaya 目前主要用于存放些个人记录，仅对熟人开放。",
        "entities": {
          "description": {
            "mentions": [
              {
                "end": 47,
                "start": 34,
                "username": "AnonChishaya"
              }
            ]
          }
        },
        "id": "1893026488662007810",
        "name": "幽沐",
        "pinned_tweet_id": "1960750862470668747",
        "profile_image_url": "https://pbs.twimg.com/profile_images/1965804929576214528/qK5YFJA-_normal.jpg",
        "protected": false,
        "public_metrics": {
          "followers_count": 556,
          "following_count": 313,
          "like_count": 7134,
          "listed_count": 3,
          "media_count": 266,
          "tweet_count": 4371
        },
        "username": "youmu0187",
        "verified": false
      }
    ]
  }
}