{
  "data": {
    "article": {},
    "attachments": {},
    "author_id": "1972363680198361088",
    "conversation_id": "1994763825133097423",
    "created_at": "2025-11-29T13:42:11.000Z",
    "edit_controls": {
      "editable_until": "2025-11-29T14:42:11.000Z",
      "edits_remaining": 5,
      "is_edit_eligible": true
    },
    "edit_history_tweet_ids": [
      "1994763825133097423"
    ],
    "entities": {},
    "geo": {},
    "id": "1994763825133097423",
    "lang": "zh",
    "note_tweet": {
      "entities": {}
    },
    "possibly_sensitive": false,
    "public_metrics": {
      "bookmark_count": 0,
      "impression_count": 0,
      "like_count": 0,
      "quote_count": 0,
      "reply_count": 0,
      "retweet_count": 0
    },
    "reply_settings": "everyone",
    "text": "自从抑郁了以后，好多东西都退步了，记忆力，碎片化，还出现了精神分裂的倾向，下个月，这些都要和医生说呢。可惜没有人提醒我。支离破碎\n不过好消息是体重出现了明显的下降，这周只吃了2餐，竟然瘦了7斤"
  },
  "includes": {
    "tweets": [
      {
        "article": {},
        "attachments": {},
        "author_id": "1972363680198361088",
        "conversation_id": "1994763825133097423",
        "created_at": "2025-11-29T13:42:11.000Z",
        "edit_controls": {
          "editable_until": "2025-11-29T14:42:11.000Z",
          "edits_remaining": 5,
          "is_edit_eligible": true
        },
        "edit_history_tweet_ids": [
          "1994763825133097423"
        ],
        "entities": {},
        "geo": {},
        "id": "1994763825133097423",
        "lang": "zh",
        "note_tweet": {
          "entities": {}
        },
        "possibly_sensitive": false,
        "public_metrics": {
          "bookmark_count": 0,
          "impression_count": 0,
          "like_count": 0,
          "quote_count": 0,
          "reply_count": 0,
          "retweet_count": 0
        },
        "reply_settings": "everyone",
        "text": "自从抑郁了以后，好多东西都退步了，记忆力，碎片化，还出现了精神分裂的倾向，下个月，这些都要和医生说呢。可惜没有人提醒我。支离破碎\n不过好消息是体重出现了明显的下降，这周只吃了2餐，竟然瘦了7斤"
      }
    ],
    "users": [
      {
        "created_at": "2025-09-28T18:12:15.000Z",
        "description": "嗯………不喜欢给自己加标签但是看起来肯定很极端的废物吧",
        "id": "1972363680198361088",
        "name": "淡水",
        "pinned_tweet_id": "1975496238289354976",
        "profile_image_url": "https://pbs.twimg.com/profile_images/1973384690410356736/1F0gknLf_normal.jpg",
        "protected": false,
        "public_metrics": {
          "followers_count": 0,
          "following_count": 0,
          "like_count": 740,
          "listed_count": 0,
          "media_count": 12,
          "tweet_count": 385
        },
        "username": "dnshu135734",
        "verified": false
      }
    ]
  }
}