{
  "data": {
    "article": {},
    "attachments": {},
    "author_id": "1972363680198361088",
    "conversation_id": "1980164649674056043",
    "created_at": "2025-10-20T06:50:16.000Z",
    "edit_controls": {
      "editable_until": "2025-10-20T07:50:16.000Z",
      "edits_remaining": 5,
      "is_edit_eligible": true
    },
    "edit_history_tweet_ids": [
      "1980164649674056043"
    ],
    "entities": {
      "urls": [
        {
          "display_url": "x.com/lianshufa/stat…",
          "end": 163,
          "expanded_url": "https://twitter.com/lianshufa/status/1979877643354005966",
          "start": 140,
          "url": "https://t.co/meikxsuQmf"
        }
      ]
    },
    "geo": {},
    "id": "1980164649674056043",
    "lang": "zh",
    "note_tweet": {
      "entities": {}
    },
    "possibly_sensitive": false,
    "public_metrics": {
      "bookmark_count": 0,
      "impression_count": 0,
      "like_count": 0,
      "quote_count": 0,
      "reply_count": 0,
      "retweet_count": 0
    },
    "referenced_tweets": [
      {
        "id": "1979877643354005966",
        "type": "quoted"
      }
    ],
    "reply_settings": "everyone",
    "text": "支持男权支持女权这种……为什么非要站队呢\n况且支持这种，永远只能以第三方的角度去支持而不是直接加入啊\n就好像支持巴勒斯坦很多人或许愿意，但真的要冒着危险去成为巴勒斯坦人的一员吗？即使是友方也仍然有可能被排斥被攻击，因为不是所有人都觉得你是同伴，仍然有人会把你视为异类，很不值得… https://t.co/meikxsuQmf"
  },
  "includes": {
    "media": [
      {
        "height": 2229,
        "media_key": "3_1979877639436337153",
        "public_metrics": {},
        "type": "photo",
        "url": "https://pbs.twimg.com/media/G3nwOSVXgAEMvUo.jpg",
        "width": 720
      },
      {
        "height": 2102,
        "media_key": "3_1979877640807841792",
        "public_metrics": {},
        "type": "photo",
        "url": "https://pbs.twimg.com/media/G3nwOXcXAAAPG5J.jpg",
        "width": 720
      }
    ],
    "tweets": [
      {
        "article": {},
        "attachments": {},
        "author_id": "1972363680198361088",
        "conversation_id": "1980164649674056043",
        "created_at": "2025-10-20T06:50:16.000Z",
        "edit_controls": {
          "editable_until": "2025-10-20T07:50:16.000Z",
          "edits_remaining": 5,
          "is_edit_eligible": true
        },
        "edit_history_tweet_ids": [
          "1980164649674056043"
        ],
        "entities": {
          "urls": [
            {
              "display_url": "x.com/lianshufa/stat…",
              "end": 163,
              "expanded_url": "https://twitter.com/lianshufa/status/1979877643354005966",
              "start": 140,
              "url": "https://t.co/meikxsuQmf"
            }
          ]
        },
        "geo": {},
        "id": "1980164649674056043",
        "lang": "zh",
        "note_tweet": {
          "entities": {}
        },
        "possibly_sensitive": false,
        "public_metrics": {
          "bookmark_count": 0,
          "impression_count": 0,
          "like_count": 0,
          "quote_count": 0,
          "reply_count": 0,
          "retweet_count": 0
        },
        "referenced_tweets": [
          {
            "id": "1979877643354005966",
            "type": "quoted"
          }
        ],
        "reply_settings": "everyone",
        "text": "支持男权支持女权这种……为什么非要站队呢\n况且支持这种，永远只能以第三方的角度去支持而不是直接加入啊\n就好像支持巴勒斯坦很多人或许愿意，但真的要冒着危险去成为巴勒斯坦人的一员吗？即使是友方也仍然有可能被排斥被攻击，因为不是所有人都觉得你是同伴，仍然有人会把你视为异类，很不值得… https://t.co/meikxsuQmf"
      },
      {
        "article": {},
        "attachments": {
          "media_keys": [
            "3_1979877639436337153",
            "3_1979877640807841792"
          ]
        },
        "author_id": "1892197607109476352",
        "conversation_id": "1979877643354005966",
        "created_at": "2025-10-19T11:49:49.000Z",
        "edit_controls": {
          "editable_until": "2025-10-19T12:49:49.000Z",
          "edits_remaining": 5,
          "is_edit_eligible": false
        },
        "edit_history_tweet_ids": [
          "1979877643354005966"
        ],
        "entities": {
          "urls": [
            {
              "display_url": "pic.x.com/AHfEZkXXEH",
              "end": 45,
              "expanded_url": "https://x.com/lianshufa/status/1979877643354005966/photo/1",
              "media_key": "3_1979877639436337153",
              "start": 22,
              "url": "https://t.co/AHfEZkXXEH"
            },
            {
              "display_url": "pic.x.com/AHfEZkXXEH",
              "end": 45,
              "expanded_url": "https://x.com/lianshufa/status/1979877643354005966/photo/1",
              "media_key": "3_1979877640807841792",
              "start": 22,
              "url": "https://t.co/AHfEZkXXEH"
            }
          ]
        },
        "geo": {},
        "id": "1979877643354005966",
        "lang": "zh",
        "note_tweet": {
          "entities": {}
        },
        "possibly_sensitive": false,
        "public_metrics": {
          "bookmark_count": 29,
          "impression_count": 59532,
          "like_count": 257,
          "quote_count": 32,
          "reply_count": 96,
          "retweet_count": 6
        },
        "reply_settings": "everyone",
        "text": "这我学校高三的一个mtf，和我打上女拳了😅 https://t.co/AHfEZkXXEH"
      }
    ],
    "users": [
      {
        "created_at": "2025-09-28T18:12:15.000Z",
        "description": "嗯………不喜欢给自己加标签但是看起来肯定很极端的废物吧",
        "id": "1972363680198361088",
        "name": "淡水",
        "pinned_tweet_id": "1975496238289354976",
        "profile_image_url": "https://pbs.twimg.com/profile_images/1973384690410356736/1F0gknLf_normal.jpg",
        "protected": false,
        "public_metrics": {
          "followers_count": 0,
          "following_count": 0,
          "like_count": 148,
          "listed_count": 0,
          "media_count": 6,
          "tweet_count": 76
        },
        "username": "dnshu135734",
        "verified": false
      },
      {
        "created_at": "2025-02-19T13:01:39.000Z",
        "description": "生日2009.10.02｜MtF🏳️‍⚧️｜家长党｜HRT开始🍥2025.06.19｜弹电吉他🎸｜个人主页:https://t.co/zZum0Dq72C｜X:@lianshufa｜QQ:2486603997｜小红书号:26722717701｜抖音号:lianshufa_｜B站UID:1228742038",
        "entities": {
          "description": {
            "mentions": [
              {
                "end": 90,
                "start": 80,
                "username": "lianshufa"
              }
            ],
            "urls": [
              {
                "display_url": "lsfself.top",
                "end": 77,
                "expanded_url": "http://lsfself.top",
                "start": 54,
                "url": "https://t.co/zZum0Dq72C"
              }
            ]
          },
          "url": {
            "urls": [
              {
                "display_url": "lsfself.top",
                "end": 23,
                "expanded_url": "http://lsfself.top",
                "start": 0,
                "url": "https://t.co/zZum0Dq72C"
              }
            ]
          }
        },
        "id": "1892197607109476352",
        "location": "北京回龙观医院门诊2层13诊室",
        "name": "lsf🍥🏳️‍⚧️",
        "pinned_tweet_id": "1975014921810395142",
        "profile_image_url": "https://pbs.twimg.com/profile_images/1955825900051947522/QKOlNb9-_normal.jpg",
        "protected": false,
        "public_metrics": {
          "followers_count": 2932,
          "following_count": 1788,
          "like_count": 1814,
          "listed_count": 4,
          "media_count": 54,
          "tweet_count": 290
        },
        "url": "https://t.co/zZum0Dq72C",
        "username": "lianshufa",
        "verified": false
      }
    ]
  }
}