{
  "data": {
    "article": {},
    "attachments": {},
    "author_id": "1972363680198361088",
    "conversation_id": "2030210779715416137",
    "created_at": "2026-03-07T09:20:59.000Z",
    "edit_controls": {
      "editable_until": "2026-03-07T10:20:59.000Z",
      "edits_remaining": 5,
      "is_edit_eligible": false
    },
    "edit_history_tweet_ids": [
      "2030212103597150223"
    ],
    "entities": {
      "mentions": [
        {
          "end": 10,
          "id": "1439465002851725314",
          "start": 0,
          "username": "sincecoco"
        }
      ]
    },
    "geo": {},
    "id": "2030212103597150223",
    "in_reply_to_user_id": "1439465002851725314",
    "lang": "zh",
    "note_tweet": {
      "entities": {}
    },
    "possibly_sensitive": false,
    "public_metrics": {
      "bookmark_count": 0,
      "impression_count": 0,
      "like_count": 0,
      "quote_count": 0,
      "reply_count": 0,
      "retweet_count": 0
    },
    "referenced_tweets": [
      {
        "id": "2030211416423096809",
        "type": "replied_to"
      }
    ],
    "reply_settings": "everyone",
    "text": "@sincecoco 但是猜错了，我是湖北的。早餐是肠粉是因为家附近有一家超级好吃的肠粉店……可以天天吃！"
  },
  "includes": {
    "tweets": [
      {
        "article": {},
        "attachments": {},
        "author_id": "1972363680198361088",
        "conversation_id": "2030210779715416137",
        "created_at": "2026-03-07T09:20:59.000Z",
        "edit_controls": {
          "editable_until": "2026-03-07T10:20:59.000Z",
          "edits_remaining": 5,
          "is_edit_eligible": false
        },
        "edit_history_tweet_ids": [
          "2030212103597150223"
        ],
        "entities": {
          "mentions": [
            {
              "end": 10,
              "id": "1439465002851725314",
              "start": 0,
              "username": "sincecoco"
            }
          ]
        },
        "geo": {},
        "id": "2030212103597150223",
        "in_reply_to_user_id": "1439465002851725314",
        "lang": "zh",
        "note_tweet": {
          "entities": {}
        },
        "possibly_sensitive": false,
        "public_metrics": {
          "bookmark_count": 0,
          "impression_count": 0,
          "like_count": 0,
          "quote_count": 0,
          "reply_count": 0,
          "retweet_count": 0
        },
        "referenced_tweets": [
          {
            "id": "2030211416423096809",
            "type": "replied_to"
          }
        ],
        "reply_settings": "everyone",
        "text": "@sincecoco 但是猜错了，我是湖北的。早餐是肠粉是因为家附近有一家超级好吃的肠粉店……可以天天吃！"
      },
      {
        "article": {},
        "attachments": {},
        "author_id": "1439465002851725314",
        "conversation_id": "2030210779715416137",
        "created_at": "2026-03-07T09:18:15.000Z",
        "edit_controls": {
          "editable_until": "2026-03-07T10:18:15.000Z",
          "edits_remaining": 5,
          "is_edit_eligible": false
        },
        "edit_history_tweet_ids": [
          "2030211416423096809"
        ],
        "entities": {
          "mentions": [
            {
              "end": 12,
              "id": "1972363680198361088",
              "start": 0,
              "username": "dnshu135734"
            }
          ]
        },
        "geo": {},
        "id": "2030211416423096809",
        "in_reply_to_user_id": "1972363680198361088",
        "lang": "zh",
        "note_tweet": {
          "entities": {}
        },
        "possibly_sensitive": false,
        "public_metrics": {
          "bookmark_count": 0,
          "impression_count": 3,
          "like_count": 0,
          "quote_count": 0,
          "reply_count": 1,
          "retweet_count": 0
        },
        "referenced_tweets": [
          {
            "id": "2030210779715416137",
            "type": "replied_to"
          }
        ],
        "reply_settings": "everyone",
        "text": "@dnshu135734 我猜你是广东的宝贝，因为肠粉是广东的！"
      }
    ],
    "users": [
      {
        "created_at": "2025-09-28T18:12:15.000Z",
        "description": "嗯………不喜欢给自己加标签但是看起来肯定很极端的废物吧",
        "id": "1972363680198361088",
        "name": "淡水",
        "pinned_tweet_id": "1975496238289354976",
        "profile_image_url": "https://pbs.twimg.com/profile_images/1973384690410356736/1F0gknLf_normal.jpg",
        "protected": false,
        "public_metrics": {
          "followers_count": 4,
          "following_count": 4,
          "like_count": 3053,
          "listed_count": 0,
          "media_count": 53,
          "tweet_count": 1244
        },
        "username": "dnshu135734",
        "verified": false
      },
      {
        "created_at": "2021-09-19T05:43:05.000Z",
        "description": "4i | 记录生活碎片，当朋友圈发 相当作家 美食分享家爱逛街 爱吃饭 争取做一个旅游博主。#日常 | #旅游｜#分享｜看黄的可以绕道走了。This is an interesting account.",
        "entities": {
          "description": {
            "hashtags": [
              {
                "end": 49,
                "start": 46,
                "tag": "日常"
              },
              {
                "end": 55,
                "start": 52,
                "tag": "旅游"
              },
              {
                "end": 59,
                "start": 56,
                "tag": "分享"
              }
            ]
          },
          "url": {
            "urls": [
              {
                "display_url": "chengzi.baby",
                "end": 23,
                "expanded_url": "http://chengzi.baby",
                "start": 0,
                "url": "https://t.co/VCsG9lSP0q"
              }
            ]
          }
        },
        "id": "1439465002851725314",
        "location": "everywhere ",
        "name": "橙子BABY",
        "pinned_tweet_id": "2029095849716822508",
        "profile_image_url": "https://pbs.twimg.com/profile_images/2021242948092919808/OmB2Fc_T_normal.jpg",
        "protected": false,
        "public_metrics": {
          "followers_count": 10713,
          "following_count": 302,
          "like_count": 1243,
          "listed_count": 28,
          "media_count": 289,
          "tweet_count": 1069
        },
        "url": "https://t.co/VCsG9lSP0q",
        "username": "sincecoco",
        "verified": true
      }
    ]
  }
}