{
  "data": {
    "article": {},
    "attachments": {},
    "author_id": "1972363680198361088",
    "conversation_id": "2019006447108194656",
    "created_at": "2026-02-04T11:13:42.000Z",
    "edit_controls": {
      "editable_until": "2026-02-04T12:13:42.000Z",
      "edits_remaining": 5,
      "is_edit_eligible": true
    },
    "edit_history_tweet_ids": [
      "2019006447108194656"
    ],
    "entities": {},
    "geo": {},
    "id": "2019006447108194656",
    "lang": "zh",
    "note_tweet": {
      "entities": {}
    },
    "possibly_sensitive": false,
    "public_metrics": {
      "bookmark_count": 0,
      "impression_count": 0,
      "like_count": 0,
      "quote_count": 0,
      "reply_count": 0,
      "retweet_count": 0
    },
    "reply_settings": "everyone",
    "text": "感情和人际交往是很危险的东西。明明成功率相当低却很吸引人的赌博。一段又一段，然后染上污浊的颜色。不想回忆这些，刻骨铭心的坏经历。\n我一直是失败者\n我为什么还活着"
  },
  "includes": {
    "tweets": [
      {
        "article": {},
        "attachments": {},
        "author_id": "1972363680198361088",
        "conversation_id": "2019006447108194656",
        "created_at": "2026-02-04T11:13:42.000Z",
        "edit_controls": {
          "editable_until": "2026-02-04T12:13:42.000Z",
          "edits_remaining": 5,
          "is_edit_eligible": true
        },
        "edit_history_tweet_ids": [
          "2019006447108194656"
        ],
        "entities": {},
        "geo": {},
        "id": "2019006447108194656",
        "lang": "zh",
        "note_tweet": {
          "entities": {}
        },
        "possibly_sensitive": false,
        "public_metrics": {
          "bookmark_count": 0,
          "impression_count": 0,
          "like_count": 0,
          "quote_count": 0,
          "reply_count": 0,
          "retweet_count": 0
        },
        "reply_settings": "everyone",
        "text": "感情和人际交往是很危险的东西。明明成功率相当低却很吸引人的赌博。一段又一段，然后染上污浊的颜色。不想回忆这些，刻骨铭心的坏经历。\n我一直是失败者\n我为什么还活着"
      }
    ],
    "users": [
      {
        "created_at": "2025-09-28T18:12:15.000Z",
        "description": "嗯………不喜欢给自己加标签但是看起来肯定很极端的废物吧",
        "id": "1972363680198361088",
        "name": "淡水",
        "pinned_tweet_id": "1975496238289354976",
        "profile_image_url": "https://pbs.twimg.com/profile_images/1973384690410356736/1F0gknLf_normal.jpg",
        "protected": false,
        "public_metrics": {
          "followers_count": 8,
          "following_count": 8,
          "like_count": 1843,
          "listed_count": 0,
          "media_count": 42,
          "tweet_count": 897
        },
        "username": "dnshu135734",
        "verified": false
      }
    ]
  }
}